{
  "treino_a": {
    "titulo": "Treino A: Membros Inferiores",
    "exercicios": [
      "Agachamento na Máquina Smith",
      "Leg Press Horizontal",
      "Cadeira Extensora",
      "Cadeira Flexora",
      "Panturrilha em Pé",
      "Abdominal Máquina"
    ],
    "progresso_esperado": {
        "Agachamento na Máquina Smith": "3x12. Barra sem anilhas.",
        "Leg Press Horizontal": "3x12 - 50kg.",
        "Cadeira Extensora": "3x15 - 20kg.",
        "Cadeira Flexora": "3x15 - 20kg.",
        "Panturrilha em Pé": "3x15",
        "Abdominal Máquina":"3x20."
    }
  },
  "treino_b": {
    "titulo": "Treino B: Superior - Empurrar",
    "exercicios": [
      "Supino com Halteres",
      "Desenvolvimento Militar (Sentado com Halteres)",
      "Elevação Lateral (Com Halteres ou Cabo)",
      "Elevação Frontal",
      "Tríceps Pulley Alto Overhead",
      "Face Pull",
      "Elevação de Pernas"
    ],
    "progresso_esperado": {
        "Supino com Halteres": "3x12. 8kg.",
        "Desenvolvimento Militar (Sentado com Halteres)": "3x12. 6kg",
        "Elevação Lateral (Com Halteres ou Cabo)": "3x15. 3kg",
        "Tríceps Pulley Alto Overhead": "3x15. 6.25kg",
        "Elevação de Pernas": "3x15.",
        "Elevação Frontal": "3x15. 3kg",
        "Face Pull": "3x15. 6.25kg"
    }
  },
  "treino_c": {
    "titulo": "Treino C: Membros Inferiores - Ênfase Posterior",
    "exercicios": [
      "Stiff (Com Halteres ou Barra)",
      "Cadeira Abdutora",
      "Cadeira Flexora",
      "Glúteo no Cabo (Kickback)",
      "Panturrilha em Pé"
    ],
    "progresso_esperado": {
        "Stiff (Com Halteres ou Barra)": "4x15reps. 15 a 20kg. TUT 4s na descida.",
        "Cadeira Abdutora": "3x20reps. 40 a 45kg. Pico de contração 2s.",
        "Cadeira Flexora": "3x20reps. 20 a 22.5kg. Rest-Pause na 3ª série.",
        "Glúteo no Cabo (Kickback)": "3x20reps. 30kg. Pico de contração 2s.",
        "Panturrilha em Pé": "4x20reps"
    }
  },
  "treino_d": {
    "titulo": "Treino D: Superior - Puxar",
    "exercicios": [
      "Puxada na Polia Alta (Pegada Pronada)",
      "Remada Baixa (Sentado)",
      "Pull Down (Corda)",
      "Rosca Direta (Barra W ou Halteres)",
      "Rosca Martelo (Halteres)"
    ],
    "progresso_esperado": {
      "Puxada na Polia Alta (Pegada Pronada)":"4x15. 25kg a 30kg. TUT na subida",
      "Remada Baixa (Sentado)":"3x15. 12.5kg a 17.5kg. Pico de contração 2s",
      "Pull Down (Corda)":"3x15. 6.75kg. DS na última.",
      "Rosca Direta (Barra W ou Halteres)":"3x15. 5kg a 6kg. RP na última.",
      "Rosca Martelo (Halteres)":"3x15. 3kg a 4kg. DS na última."
    }
  },
  "treino_e": {
    "titulo": "Treino E: Corpo Inteiro - Bi-Set",
    "exercicios": [
      "Cadeira Extensora", 
      "Remada Curvada (Halteres/Barra)", 
      "Supino com Halteres", 
      "Stiff (Com Halteres ou Barra)", 
      "Elevação Lateral (Com Halteres ou Cabo)", 
      "Cadeira Abdutora", 
      "Prancha Ventral"
    ],
    "progresso_esperado": {
      "Cadeira Extensora": "Aumentar a carga para 35kg e focar no pico de contração.",
      "Remada Curvada (Halteres/Barra)": "Tentar carga máxima com boa forma.",
      "Supino com Halteres": "Aumentar para 10kg.",
      "Stiff (Com Halteres ou Barra)": "Fazer TUT 4s e tentar aumentar a carga de 20kg.",
      "Prancha Ventral": "Manter por 60s e focar na respiração."
    }
  }
}
